{
  "credit": "Made by Enchanted Games (https://enchanted.games)",
  "parent": "item/generated",
  "display": {
    "thirdperson_righthand": {
      "rotation": [-0.78, -2.1, 35],
      "translation": [-0.5, 2.75, 1],
      "scale": [0.55, 0.55, 0.55]
    },
    "thirdperson_lefthand": {
      "rotation": [-0.78, 177.9, -35],
      "translation": [-0.5, 2.75, 1],
      "scale": [0.55, 0.55, 0.55]
    },
    "firstperson_righthand": {
      "rotation": [-86, -76, -69],
      "translation": [1.63, 2.45, 6.83],
      "scale": [0.68, 0.68, 0.68]
    },
    "firstperson_lefthand": {
      "rotation": [-86, 106, 69],
      "translation": [1.63, 2.45, 6.83],
      "scale": [0.68, 0.68, 0.68]
    }
  }
}
